get_mseed_data/__init__.py
get_mseed_data/get_mseed.py
get_mseed_data/get_mseed_utils.py
get_mseed_data-0.3.1.dist-info/LICENSE
get_mseed_data-0.3.1.dist-info/METADATA
get_mseed_data-0.3.1.dist-info/WHEEL
get_mseed_data-0.3.1.dist-info/top_level.txt
get_mseed_data-0.3.1.dist-info/RECORD
